{
  "name": "Themer Dark",
  "type": "dark",
  "colors": {
    "focusBorder": "#9b6152",
    "foreground": "#e4dec1",
    "widget.shadow": "#000000",
    "selection.background": "#444c4b",
    "errorForeground": "#e4dec1",
    "button.background": "#121E28",
    "button.foreground": "#e4dec1",
    "button.hoverBackground": "#243c51",
    "dropdown.background": "#242e34",
    "dropdown.border": "#242e34",
    "dropdown.foreground": "#c4c1a9",
    "input.background": "#242e34",
    "input.border": "#242e34",
    "input.foreground": "#c4c1a9",
    "input.placeholderForeground": "#444c4b",
    "inputOption.activeBorder": "#b08664",
    "inputValidation.errorBackground": "#242e34",
    "inputValidation.errorBorder": "#e4dec1",
    "inputValidation.infoBackground": "#242e34",
    "inputValidation.infoBorder": "#aa662d",
    "inputValidation.warningBackground": "#242e34",
    "inputValidation.warningBorder": "#e8deae",
    "scrollbar.shadow": "#121920",
    "scrollbarSlider.activeBackground": "#a4a3927f",
    "scrollbarSlider.background": "#6469637f",
    "scrollbarSlider.hoverBackground": "#84867a7f",
    "badge.foreground": "#e4dec1",
    "badge.background": "#9b6152",
    "progressBar.background": "#e5c27a",
    "list.activeSelectionBackground": "#243c51",
    "list.activeSelectionForeground": "#e4dec1",
    "list.dropBackground": "#646963",
    "list.focusBackground": "#646963",
    "list.highlightForeground": "#dfca9d",
    "list.hoverBackground": "#242e34",
    "list.inactiveSelectionBackground": "#242e34",
    "list.inactiveSelectionForeground": "#e4dec1",
    "list.hoverForeground": "#a4a392",
    "list.focusForeground": "#121920",
    "activityBar.background": "#121920",
    "activityBar.dropBackground": "#242e34",
    "activityBar.foreground": "#a4a392",
    "activityBar.border": "#121920",
    "activityBarBadge.background": "#9b6152",
    "activityBarBadge.foreground": "#121920",
    "sideBar.background": "#121920",
    "sideBar.foreground": "#c4c1a9",
    "sideBar.border": "#242e34",
    "sideBarTitle.foreground": "#a4a392",
    "sideBarSectionHeader.background": "#444c4b",
    "sideBarSectionHeader.foreground": "#c4c1a9",
    "editorPane.background": "#121920",
    "editorGroup.emptyBackground": "#121920",
    "editorGroup.border": "#242e34",
    "editorGroup.focusedEmptyBorder": "#242e34",
    "editorGroup.dropBackground": "#444c4b7f",
    "editorGroupHeader.noTabsBackground": "#121920",
    "editorGroupHeader.tabsBackground": "#121920",
    "editorGroupHeader.tabsBorder": "#121920",
    "tab.activeBackground": "#242e34",
    "tab.activeForeground": "#a4a392",
    "tab.border": "#121920",
    "tab.inactiveBackground": "#121920",
    "tab.inactiveForeground": "#84867a",
    "tab.unfocusedActiveForeground": "#646963",
    "tab.unfocusedInactiveForeground": "#444c4b",
    "editor.background": "#121920",
    "editor.foreground": "#e4dec1",
    "editorLineNumber.foreground": "#444c4b",
    "editorCursor.foreground": "#9b6152",
    "editor.selectionBackground": "#aa662d33",
    "editor.selectionHighlightBackground": "#242e34",
    "editor.inactiveSelectionBackground": "#aa662d33",
    "editor.wordHighlightBackground": "#9b61527f",
    "editor.wordHighlightStrongBackground": "#9a47317f",
    "editor.findMatchBackground": "#dfca9d7f",
    "editor.findMatchHighlightBackground": "#dfca9d3f",
    "editor.findRangeHighlightBackground": "#242e34",
    "editor.hoverHighlightBackground": "#444c4b",
    "editor.lineHighlightBackground": "#121920",
    "editor.lineHighlightBorder": "#242e34",
    "editorLink.activeForeground": "#b08664",
    "editor.rangeHighlightBackground": "#242e34",
    "editorWhitespace.foreground": "#242e34",
    "editorIndentGuide.background": "#242e34",
    "editorIndentGuide.activeBackground": "#444c4b",
    "editorRuler.foreground": "#242e34",
    "editorCodeLens.foreground": "#a4a392",
    "editorBracketMatch.background": "#242e34",
    "editorBracketMatch.border": "#242e34",
    "editorOverviewRuler.border": "#242e34",
    "editorOverviewRuler.findMatchForeground": "#dfca9dbf",
    "editorOverviewRuler.rangeHighlightForeground": "#444c4bbf",
    "editorOverviewRuler.selectionHighlightForeground": "#242e34bf",
    "editorOverviewRuler.wordHighlightForeground": "#444c4bbf",
    "editorOverviewRuler.wordHighlightStrongForeground": "#646963bf",
    "editorOverviewRuler.modifiedForeground": "#dfca9d7f",
    "editorOverviewRuler.addedForeground": "#e5c27a7f",
    "editorOverviewRuler.deletedForeground": "#e4dec17f",
    "editorOverviewRuler.errorForeground": "#e4dec17f",
    "editorOverviewRuler.warningForeground": "#e8deae7f",
    "editorOverviewRuler.infoForeground": "#aa662d7f",
    "editorError.foreground": "#e4dec1",
    "editorError.border": "#e4dec1",
    "editorWarning.foreground": "#e8deae",
    "editorWarning.border": "#c4c1a9",
    "editorGutter.background": "#121920",
    "editorGutter.modifiedBackground": "#dfca9d",
    "editorGutter.addedBackground": "#e5c27a",
    "editorGutter.deletedBackground": "#e4dec1",
    "diffEditor.insertedTextBackground": "#e5c27a20",
    "diffEditor.removedTextBackground": "#e4dec120",
    "editorWidget.background": "#242e34",
    "editorWidget.border": "#242e34",
    "editorSuggestWidget.background": "#242e34",
    "editorSuggestWidget.border": "#242e34",
    "editorSuggestWidget.foreground": "#c4c1a9",
    "editorSuggestWidget.highlightForeground": "#9a4731",
    "editorSuggestWidget.selectedBackground": "#444c4b",
    "editorHoverWidget.background": "#242e34",
    "editorHoverWidget.border": "#242e34",
    "debugExceptionWidget.background": "#242e34",
    "debugExceptionWidget.border": "#242e34",
    "editorMarkerNavigation.background": "#242e34",
    "editorMarkerNavigationError.background": "#e4dec1",
    "editorMarkerNavigationWarning.background": "#e8deae",
    "peekView.border": "#9a4731",
    "peekViewEditor.background": "#242e34",
    "peekViewEditorGutter.background": "#242e34",
    "peekViewEditor.matchHighlightBackground": "#dfca9d",
    "peekViewResult.background": "#242e34",
    "peekViewResult.fileForeground": "#c4c1a9",
    "peekViewResult.lineForeground": "#444c4b",
    "peekViewResult.matchHighlightBackground": "#dfca9d",
    "peekViewResult.selectionBackground": "#646963",
    "peekViewResult.selectionForeground": "#e4dec1",
    "peekViewTitle.background": "#444c4b",
    "peekViewTitleDescription.foreground": "#a4a392",
    "peekViewTitleLabel.foreground": "#e4dec1",
    "merge.currentHeaderBackground": "#b08664",
    "merge.currentContentBackground": "#b086647f",
    "merge.incomingHeaderBackground": "#aa662d",
    "merge.incomingContentBackground": "#aa662d7f",
    "merge.border": "#84867a",
    "editorOverviewRuler.currentContentForeground": "#b08664",
    "editorOverviewRuler.incomingContentForeground": "#aa662d",
    "panel.background": "#121920",
    "panel.border": "#242e34",
    "panelTitle.activeBorder": "#646963",
    "panelTitle.activeForeground": "#c4c1a9",
    "panelTitle.inactiveForeground": "#84867a",
    "statusBar.background": "#121E28",
    "statusBar.foreground": "#e4dec1",
    "statusBar.border": "#242e34",
    "statusBar.debuggingBackground": "#e8deae",
    "statusBar.debuggingForeground": "#121920",
    "statusBar.debuggingBorder": "#e8deae7f",
    "statusBar.noFolderBackground": "#9b6152",
    "statusBar.noFolderForeground": "#121920",
    "statusBar.noFolderBorder": "#9b61527f",
    "statusBarItem.activeBackground": "#b08664",
    "statusBarItem.hoverBackground": "#e5c27a",
    "statusBarItem.prominentBackground": "#b08664",
    "statusBarItem.prominentHoverBackground": "#e5c27a",
    "titleBar.activeBackground": "#121920",
    "titleBar.activeForeground": "#a4a392",
    "titleBar.inactiveBackground": "#121920",
    "titleBar.inactiveForeground": "#646963",
    "notification.background": "#242e34",
    "notification.foreground": "#e4dec1",
    "notification.buttonBackground": "#aa662d",
    "notification.buttonHoverBackground": "#b08664",
    "notification.buttonForeground": "#121920",
    "notification.infoBackground": "#aa662d",
    "notification.infoForeground": "#121920",
    "notification.warningBackground": "#e8deae",
    "notification.warningForeground": "#121920",
    "notification.errorBackground": "#e4dec1",
    "notification.errorForeground": "#121920",
    "extensionButton.prominentForeground": "#121920",
    "extensionButton.prominentBackground": "#aa662d",
    "extensionButton.prominentHoverBackground": "#b08664",
    "pickerGroup.border": "#a4a392",
    "pickerGroup.foreground": "#e4dec1",
    "terminal.background": "#121920",
    "terminal.foreground": "#c4c1a9",
    "terminal.ansiBlack": "#121920",
    "terminal.ansiBlue": "#aa662d",
    "terminal.ansiBrightBlack": "#242e34",
    "terminal.ansiBrightBlue": "#aa662d",
    "terminal.ansiBrightCyan": "#b08664",
    "terminal.ansiBrightGreen": "#b08664",
    "terminal.ansiBrightMagenta": "#9a4731",
    "terminal.ansiBrightRed": "#e8deae",
    "terminal.ansiBrightWhite": "#e4dec1",
    "terminal.ansiBrightYellow": "#dfca9d",
    "terminal.ansiCyan": "#b08664",
    "terminal.ansiGreen": "#e5c27a",
    "terminal.ansiMagenta": "#9a4731",
    "terminal.ansiRed": "#e4dec1",
    "terminal.ansiWhite": "#c4c1a9",
    "terminal.ansiYellow": "#dfca9d",
    "terminal.selectionBackground": "#aa662d7f",
    "terminalCursor.background": "#242e34",
    "terminalCursor.foreground": "#a4a392",
    "debugToolBar.background": "#242e34",
    "welcomePage.buttonBackground": "#242e34",
    "welcomePage.buttonHoverBackground": "#444c4b",
    "walkThrough.embeddedEditorBackground": "#121920",
    "gitDecoration.modifiedResourceForeground": "#dfca9d",
    "gitDecoration.deletedResourceForeground": "#e4dec1",
    "gitDecoration.untrackedResourceForeground": "#9b6152",
    "gitDecoration.ignoredResourceForeground": "#646963",
    "gitDecoration.conflictingResourceForeground": "#b08664"
  },
  "tokenColors": [
    {
      "settings": {
        "background": "#121920",
        "foreground": "#c4c1a9",
        "selectionBorder": "#a4a392",
        "findHighlight": "#dfca9d",
        "findHighlightForeground": "#121920",
        "activeGuide": "#e8deae",
        "bracketsForeground": "#c4c1a97F",
        "bracketsOptions": "stippled_underline",
        "bracketsContentsForeground": "#c4c1a97F",
        "tagsOptions": "stippled_underline"
      }
    },
    {
      "name": "Comment",
      "scope": "comment",
      "settings": {
        "foreground": "#646963"
      }
    },
    {
      "name": "Constant",
      "scope": "constant",
      "settings": {
        "foreground": "#9a4731"
      }
    },
    {
      "name": "Entity",
      "scope": "entity",
      "settings": {
        "foreground": "#b08664"
      }
    },
    {
      "name": "Invalid",
      "scope": "invalid",
      "settings": {
        "background": "#e4dec1",
        "foreground": "#242e34"
      }
    },
    {
      "name": "Keyword",
      "scope": "keyword",
      "settings": {
        "foreground": "#9b6152"
      }
    },
    {
      "name": "Storage",
      "scope": "storage",
      "settings": {
        "foreground": "#9a4731"
      }
    },
    {
      "name": "String",
      "scope": "string",
      "settings": {
        "foreground": "#e5c27a"
      }
    },
    {
      "name": "Support",
      "scope": "support",
      "settings": {
        "foreground": "#b08664"
      }
    },
    {
      "name": "Variable",
      "scope": "variable",
      "settings": {
        "foreground": "#e4dec1"
      }
    },
    {
      "name": "Markup Heading",
      "scope": "markup.heading",
      "settings": {
        "foreground": "#b08664"
      }
    },
    {
      "name": "Markup Deleted",
      "scope": "markup.deleted",
      "settings": {
        "foreground": "#e4dec1"
      }
    },
    {
      "name": "Markup Inserted",
      "scope": "markup.inserted",
      "settings": {
        "foreground": "#e5c27a"
      }
    },
    {
      "name": "Markup Changed",
      "scope": "markup.changed",
      "settings": {
        "foreground": "#dfca9d"
      }
    },
    {
      "name": "Markup Underline",
      "scope": "markup.underline",
      "settings": {
        "fontStyle": "underline"
      }
    },
    {
      "name": "Markup Underline Link",
      "scope": "markup.underline.link",
      "settings": {
        "foreground": "#aa662d"
      }
    },
    {
      "name": "Markup List",
      "scope": "markup.list",
      "settings": {
        "foreground": "#e4dec1"
      }
    },
    {
      "name": "Markup Raw",
      "scope": "markup.raw",
      "settings": {
        "foreground": "#9a4731"
      }
    }
  ]
}